MANIFEST.in
README.rst
setup.py
test_requirements.txt
sockfilter/__init__.py
sockfilter/__init__.pyc
sockfilter/address.py
sockfilter/address.pyc
sockfilter/error.py
sockfilter/error.pyc
sockfilter/fake.py
sockfilter/fake.pyc
sockfilter/real.py
sockfilter/real.pyc
sockfilter/util.py
sockfilter/util.pyc
sockfilter.egg-info/PKG-INFO
sockfilter.egg-info/SOURCES.txt
sockfilter.egg-info/dependency_links.txt
sockfilter.egg-info/top_level.txt