Metadata-Version: 1.0
Name: sockfilter
Version: 1.3
Summary: Block socket creation by host/port.
Home-page: https://github.com/cardforcoin/sockfilter
Author: Chris Martin
Author-email: ch.martin@gmail.com
License: MIT
Platform: UNKNOWN
